ATF/__init__.py
Attention_and_Transformers/__init__.py
Attention_and_Transformers/MobileViT_v1/BaseLayers.py
Attention_and_Transformers/MobileViT_v1/__init__.py
Attention_and_Transformers/MobileViT_v1/mobile_vit_v1.py
Attention_and_Transformers/MobileViT_v1/mobile_vit_v1_block.py
Attention_and_Transformers/MobileViT_v1/multihead_self_attention_2D.py
Attention_and_Transformers/MobileViT_v1/utils.py
Attention_and_Transformers/MobileViT_v2/BaseLayers.py
Attention_and_Transformers/MobileViT_v2/__init__.py
Attention_and_Transformers/MobileViT_v2/linear_attention.py
Attention_and_Transformers/MobileViT_v2/mobile_vit_v2.py
Attention_and_Transformers/MobileViT_v2/mobile_vit_v2_block.py
Attention_and_Transformers/MobileViT_v2/utils.py
Attention_and_Transformers/ViT/__init__.py
Attention_and_Transformers/ViT/multihead_self_attention.py
Attention_and_Transformers/ViT/vision_transformer.py
Attention_and_Transformers-0.0.15.dist-info/LICENSE
Attention_and_Transformers-0.0.15.dist-info/METADATA
Attention_and_Transformers-0.0.15.dist-info/WHEEL
Attention_and_Transformers-0.0.15.dist-info/top_level.txt
Attention_and_Transformers-0.0.15.dist-info/RECORD
