Metadata-Version: 2.1
Name: Attention-and-Transformers
Version: 0.0.15
Summary: Building attention mechanisms and Transformer models from scratch. Alias ATF.
Home-page: https://github.com/veb-101/Attention-and-Transformers
Author: Vaibhav Singh
Author-email: vaibhav.singh.3001@gmail.com
License: Apache 2.0
Keywords: tensorflow keras attention transformers
Classifier: Development Status :: 3 - Alpha
Classifier: Intended Audience :: Developers
Classifier: Intended Audience :: Science/Research
Classifier: License :: OSI Approved :: Apache Software License
Classifier: Programming Language :: Python :: 3.7
Classifier: Programming Language :: Python :: 3.8
Classifier: Programming Language :: Python :: 3.9
Classifier: Programming Language :: Python :: 3.10
Classifier: Topic :: Scientific/Engineering
Classifier: Topic :: Scientific/Engineering :: Artificial Intelligence
Classifier: Topic :: Software Development
Classifier: Topic :: Software Development :: Libraries
Classifier: Topic :: Software Development :: Libraries :: Python Modules
Requires-Python: >=3.7,<3.11.*
License-File: LICENSE
Requires-Dist: tensorflow-datasets
Requires-Dist: livelossplot
Requires-Dist: Pillow
Requires-Dist: opencv-contrib-python
Requires-Dist: pandas
Requires-Dist: scikit-learn
Requires-Dist: matplotlib
Requires-Dist: scikit-image
Requires-Dist: tensorflow-addons ; platform_machine != "aarch64" and platform_machine != "aarch32"
Requires-Dist: tensorflow (>=2.10.0) ; platform_system != "Darwin"
Requires-Dist: tensorflow-macos ; platform_system == "Darwin"
